ichika-0.0.8.dist-info/METADATA
ichika-0.0.8.dist-info/WHEEL
ichika-0.0.8.dist-info/license_files/LICENSE
ichika/client.py
ichika/core.pyi
ichika/build_info.py
ichika/exceptions.py
ichika/structs.py
ichika/graia/__init__.py
ichika/graia/event.py
ichika/scripts/device/generator.py
ichika/scripts/device/data.json
ichika/scripts/device/__init__.py
ichika/scripts/device/converter.py
ichika/scripts/__init__.py
ichika/event_defs.py
ichika/__init__.py
ichika/message/_serializer.py
ichika/message/_sealed.py
ichika/message/elements.py
ichika/message/__init__.py
ichika/utils.py
ichika/login/password.py
ichika/login/__init__.py
ichika/login/qrcode/__init__.py
ichika/login/qrcode/render/__init__.py
ichika/login/qrcode/render/dense1x2.py
ichika/core.abi3.so
ichika-0.0.8.dist-info/RECORD
