Metadata-Version: 2.1
Name: ichika
Version: 0.0.8
Classifier: Development Status :: 2 - Pre-Alpha
Classifier: License :: OSI Approved :: GNU Affero General Public License v3
Classifier: Natural Language :: Chinese (Simplified)
Classifier: Programming Language :: Rust
Classifier: Programming Language :: Python :: Implementation :: CPython
Classifier: Topic :: Communications
Classifier: Programming Language :: Python :: 3
Classifier: Programming Language :: Python :: 3.8
Classifier: Programming Language :: Python :: 3.9
Classifier: Programming Language :: Python :: 3.10
Classifier: Programming Language :: Python :: 3.11
Requires-Dist: loguru~=0.6.0
Requires-Dist: dacite>=1.6.0
Requires-Dist: graia-amnesia>=0.7.0
Requires-Dist: aiohttp>=3.8.3
Requires-Dist: graia-broadcast>=0.19.2; extra == 'graia'
Requires-Dist: launart>=0.6.3; extra == 'graia'
Requires-Dist: creart>=0.2.2; extra == 'graia'
Requires-Dist: creart-graia>=0.1.5; extra == 'graia'
Requires-Dist: graiax-shortcut>=0.2.1; extra == 'graia'
Provides-Extra: graia
License-File: LICENSE
Summary: 基于 RICQ 的轻量级 Python QQ 自动化框架。
Keywords: graia,bot,qq,framework,ricq,ichika
Author: BlueGlassBlock <blueglassblock@outlook.com>
Author-email: BlueGlassBlock <blueglassblock@outlook.com>
License: AGPL-3.0
Requires-Python: >=3.8
